deep_profane/__init__.py
deep_profane/model_weights.py
deep_profane/tfhub_bert_handle.py
deep_profane/validator.py
deep_profane-0.0.3.dist-info/METADATA
deep_profane-0.0.3.dist-info/WHEEL
deep_profane-0.0.3.dist-info/licenses/LICENSE
deep_profane-0.0.3.dist-info/RECORD
