Metadata-Version: 2.1
Name: deep-profane
Version: 0.0.3
Summary: Profanity and offensive language detection using deep learning models.
Project-URL: Homepage, https://github.com/daoern/deep-profane
Project-URL: Bug Tracker, https://github.com/daoern/deep-profane/issues
Author-email: daoern <mail@daoern.com>
License: MIT License
Classifier: License :: OSI Approved :: MIT License
Classifier: Operating System :: OS Independent
Classifier: Programming Language :: Python :: 3
Requires-Python: >=3.7
Requires-Dist: keras
Requires-Dist: requests
Requires-Dist: tensorflow
Requires-Dist: tensorflow-hub
Requires-Dist: tensorflow-text
Requires-Dist: tqdm
